accelerator_utils/__init__.py
accelerator_utils/file_interfaces.py
accelerator_utils/plotting.py
accelerator_utils-0.0.4.dist-info/LICENSE.txt
accelerator_utils-0.0.4.dist-info/METADATA
accelerator_utils-0.0.4.dist-info/WHEEL
accelerator_utils-0.0.4.dist-info/top_level.txt
accelerator_utils-0.0.4.dist-info/RECORD
