Metadata-Version: 2.1
Name: accelerator-utils
Version: 0.0.4
Summary: Sharing useful python functions for accelerator physics with the public
Author-email: "Christopher M. Pierce" <contact@chris-pierce.com>
License: BSD 3-Clause License
Classifier: Programming Language :: Python :: 3
Classifier: Operating System :: OS Independent
Requires-Python: >=3.8
License-File: LICENSE.txt
Requires-Dist: pandas
Requires-Dist: numpy
Requires-Dist: pillow
Requires-Dist: scipy
Requires-Dist: matplotlib
Provides-Extra: tests
Requires-Dist: pytest ; extra == 'tests'
